ptsl/PTSL_pb2.py
ptsl/PTSL_pb2.pyi
ptsl/PTSL_pb2_grpc.py
ptsl/__init__.py
ptsl/__main__.py
ptsl/builders/create_session_builder.py
ptsl/builders/export_text_builder.py
ptsl/builders/import_builder.py
ptsl/client.py
ptsl/engine.py
ptsl/errors.py
ptsl/ops/__init__.py
ptsl/ops/authorize_connection.py
ptsl/ops/clear.py
ptsl/ops/clear_special.py
ptsl/ops/close_session.py
ptsl/ops/consolidate_clip.py
ptsl/ops/copy.py
ptsl/ops/copy_special.py
ptsl/ops/create_fades_based_on_preset.py
ptsl/ops/create_new_tracks.py
ptsl/ops/create_session.py
ptsl/ops/cut.py
ptsl/ops/cut_special.py
ptsl/ops/edit_mode.py
ptsl/ops/edit_tool.py
ptsl/ops/export_clips_as_files.py
ptsl/ops/export_mix.py
ptsl/ops/export_selected_tracks_as_aaf_omf.py
ptsl/ops/export_session_info_as_text.py
ptsl/ops/extend_selection_to_target_tracks.py
ptsl/ops/get_dynamic_properties.py
ptsl/ops/get_file_location.py
ptsl/ops/get_playback_mode.py
ptsl/ops/get_ptsl_version.py
ptsl/ops/get_record_mode.py
ptsl/ops/get_session_audio_format.py
ptsl/ops/get_session_audio_rate_pull_settings.py
ptsl/ops/get_session_bit_depth.py
ptsl/ops/get_session_feet_frames_rate.py
ptsl/ops/get_session_interleaved_state.py
ptsl/ops/get_session_length.py
ptsl/ops/get_session_name.py
ptsl/ops/get_session_path.py
ptsl/ops/get_session_sample_rate.py
ptsl/ops/get_session_start_time.py
ptsl/ops/get_session_time_code_rate.py
ptsl/ops/get_session_video_rate_pull_settings.py
ptsl/ops/get_task_status.py
ptsl/ops/get_track_list.py
ptsl/ops/get_transport_armed.py
ptsl/ops/get_transport_state.py
ptsl/ops/host_ready_check.py
ptsl/ops/import_command.py
ptsl/ops/memory_locations.py
ptsl/ops/open_session.py
ptsl/ops/operation.py
ptsl/ops/paste.py
ptsl/ops/paste_special.py
ptsl/ops/pt_202406_additions.py
ptsl/ops/refresh_all_modified_audio_files.py
ptsl/ops/refresh_target_audio_files.py
ptsl/ops/register_connection.py
ptsl/ops/rename_selected_clip.py
ptsl/ops/rename_target_clip.py
ptsl/ops/rename_target_track.py
ptsl/ops/save_session.py
py_ptsl-600.2.0.dist-info/METADATA
py_ptsl-600.2.0.dist-info/WHEEL
py_ptsl-600.2.0.dist-info/licenses/LICENSE
py_ptsl-600.2.0.dist-info/RECORD
