Metadata-Version: 2.4
Name: py-ptsl
Version: 600.2.0
Summary: Native Python PTSL (Pro Tools Scripting Library) RPC interface
License-Expression: BSD-3-Clause
License-File: LICENSE
Keywords: pro tools,scripting,grpc,automation,avid
Author: Jamie Hardt
Author-email: jamiehardt@me.com
Requires-Python: >=3.9,<4.0
Classifier: Development Status :: 4 - Beta
Classifier: License :: OSI Approved :: BSD License
Classifier: Topic :: Software Development :: Libraries :: Python Modules
Classifier: Programming Language :: Python :: 3.13
Classifier: Programming Language :: Python :: 3.12
Classifier: Programming Language :: Python :: 3.11
Classifier: Programming Language :: Python :: 3.10
Classifier: Programming Language :: Python :: 3.9
Classifier: Topic :: Multimedia :: Sound/Audio :: Editors
Provides-Extra: doc
Requires-Dist: flake8 (>=7.3.0,<8.0.0)
Requires-Dist: grpcio (==1.76.0)
Requires-Dist: protobuf (>=6.31.1,<6.32.0)
Requires-Dist: pytest (>=8.4.2,<9.0.0)
Requires-Dist: sphinx (>=5.3.0) ; extra == "doc"
Requires-Dist: sphinx_rtd_theme (>=1.1.1) ; extra == "doc"
Project-URL: Tracker, https://github.com/iluvcapra/py-ptsl/issues
